pubmed/__init__.py
pubmed/literature.py
pubmed-0.0.1.post0.dist-info/DESCRIPTION.rst
pubmed-0.0.1.post0.dist-info/entry_points.txt
pubmed-0.0.1.post0.dist-info/METADATA
pubmed-0.0.1.post0.dist-info/metadata.json
pubmed-0.0.1.post0.dist-info/RECORD
pubmed-0.0.1.post0.dist-info/top_level.txt
pubmed-0.0.1.post0.dist-info/WHEEL
pubmed-0.0.1.post0.dist-info/zip-safe
