Metadata-Version: 2.0
Name: pubmed
Version: 0.0.1.post0
Summary: Get literature information via PubMed ID
Home-page: http://github.com/twz915/pubmed
Author: Weizhong Tu
Author-email: mail@tuweizhong.com
License: MIT
Keywords: pubmed literature reference PMID
Platform: UNKNOWN
Classifier: Development Status :: 5 - Production/Stable
Classifier: Intended Audience :: Science/Research
Classifier: License :: OSI Approved :: MIT License
Classifier: Programming Language :: Python :: 2.7
Requires-Dist: beautifulsoup4
Requires-Dist: pyquery
